{
   "image_filename": "0009.jpg",
   "complete": null,
   "labels": [
      {
         "size": {
            "y": 31.008435903162933,
            "x": 47.50228478782407
         },
         "object_id": 1,
         "centre": {
            "y": 217.48398132947952,
            "x": 377.5399207632348
         },
         "label_class": "container",
         "label_type": "box"
      },
      {
         "size": {
            "y": 39.58523732318673,
            "x": 82.46924442330567
         },
         "object_id": 2,
         "centre": {
            "y": 204.61877919944382,
            "x": 458.3597802980744
         },
         "label_class": "container",
         "label_type": "box"
      },
      {
         "size": {
            "y": 32.32794381393583,
            "x": 65.97539553864453
         },
         "object_id": 3,
         "centre": {
            "y": 179.87800587245215,
            "x": 466.60670474040495
         },
         "label_class": "container",
         "label_type": "box"
      },
      {
         "size": {
            "y": 38.26572941241383,
            "x": 82.46924442330567
         },
         "object_id": 4,
         "centre": {
            "y": 232.32844532567452,
            "x": 457.7000263426879
         },
         "label_class": "container",
         "label_type": "box"
      },
      {
         "size": {
            "y": 37.60597545702743,
            "x": 79.83022860175993
         },
         "object_id": 5,
         "centre": {
            "y": 258.38872656343915,
            "x": 457.7000263426879
         },
         "label_class": "container",
         "label_type": "box"
      },
      {
         "size": {
            "y": 36.28646754625447,
            "x": 80.48998255714633
         },
         "object_id": 6,
         "centre": {
            "y": 286.7581466450563,
            "x": 458.68965727576756
         },
         "label_class": "container",
         "label_type": "box"
      },
      {
         "size": {
            "y": 37.6059754570274,
            "x": 76.53145882482767
         },
         "object_id": 7,
         "centre": {
            "y": 313.80805881590055,
            "x": 456.0506414542218
         },
         "label_class": "container",
         "label_type": "box"
      },
      {
         "size": {
            "y": 25.730404260071367,
            "x": 44.203515010891834
         },
         "object_id": 8,
         "centre": {
            "y": 228.04004461566262,
            "x": 205.6740153850658
         },
         "label_class": "container",
         "label_type": "box"
      },
      {
         "size": {
            "y": 22.431634483139135,
            "x": 50.8010545647563
         },
         "object_id": 9,
         "centre": {
            "y": 295.66482504277326,
            "x": 192.47893627733686
         },
         "label_class": "container",
         "label_type": "box"
      },
      {
         "size": {
            "y": 30.34868194777647,
            "x": 54.759578297074995
         },
         "object_id": 10,
         "centre": {
            "y": 314.79768974898025,
            "x": 193.79844418810976
         },
         "label_class": "container",
         "label_type": "box"
      },
      {
         "size": {
            "y": 27.049912170844266,
            "x": 53.44007038630207
         },
         "object_id": 11,
         "centre": {
            "y": 334.92018538826676,
            "x": 192.47893627733686
         },
         "label_class": "container",
         "label_type": "box"
      },
      {
         "size": {
            "y": 13.854833063115336,
            "x": 16.493848884661134
         },
         "object_id": 12,
         "centre": {
            "y": 296.654455975853,
            "x": 160.15099246340102
         },
         "label_class": "container",
         "label_type": "box"
      },
      {
         "size": {
            "y": 16.493848884661134,
            "x": 33.6474517247087
         },
         "object_id": 13,
         "centre": {
            "y": 233.31807625875422,
            "x": 166.08877806187905
         },
         "label_class": "container",
         "label_type": "box"
      }
   ]
}