{
   "labels": [
      {
         "object_id": 1,
         "label_class": "container",
         "size": {
            "x": 120.61332727468749,
            "y": 40.778791602394364
         },
         "label_type": "box",
         "centre": {
            "x": 60.98458133835811,
            "y": 262.93239677738535
         }
      },
      {
         "object_id": 2,
         "label_class": "container",
         "size": {
            "x": 120.03897809718897,
            "y": 42.50183913488988
         },
         "label_type": "box",
         "centre": {
            "x": 184.7568290892874,
            "y": 259.199127123645
         }
      },
      {
         "object_id": 3,
         "label_class": "container",
         "size": {
            "x": 224.57052840191815,
            "y": 41.92748995739137
         },
         "label_type": "box",
         "centre": {
            "x": 359.358979048835,
            "y": 257.76325417989875
         }
      },
      {
         "object_id": 4,
         "label_class": "container",
         "size": {
            "x": 122.91072398468154,
            "y": 50.542727619869055
         },
         "label_type": "box",
         "centre": {
            "x": 61.558930515856616,
            "y": 216.69728798875514
         }
      },
      {
         "object_id": 5,
         "label_class": "container",
         "size": {
            "x": 125.20812069467557,
            "y": 49.39402926487202
         },
         "label_type": "box",
         "centre": {
            "x": 185.04400367803666,
            "y": 214.3998912787611
         }
      },
      {
         "object_id": 6,
         "label_class": "container",
         "size": {
            "x": 225.7192267569152,
            "y": 50.542727619869055
         },
         "label_type": "box",
         "centre": {
            "x": 358.210280693838,
            "y": 212.10249456876704
         }
      },
      {
         "object_id": 7,
         "label_class": "container",
         "size": {
            "x": 74.09104389730805,
            "y": 58.009266927349685
         },
         "label_type": "box",
         "centre": {
            "x": 462.16748182106863,
            "y": 148.06256127768296
         }
      },
      {
         "object_id": 8,
         "label_class": "container",
         "size": {
            "x": 202.7452596569747,
            "y": 52.84012432986307
         },
         "label_type": "box",
         "centre": {
            "x": 325.47237757642284,
            "y": 162.70846530389503
         }
      },
      {
         "object_id": 9,
         "label_class": "container",
         "size": {
            "x": 122.33637480718303,
            "y": 55.13752103985712
         },
         "label_type": "box",
         "centre": {
            "x": 162.35721116684545,
            "y": 162.70846530389503
         }
      },
      {
         "object_id": 10,
         "label_class": "container",
         "size": {
            "x": 101.0854552397381,
            "y": 53.414473507361606
         },
         "label_type": "box",
         "centre": {
            "x": 50.646296143384895,
            "y": 162.99563989264428
         }
      },
      {
         "object_id": 11,
         "label_class": "container",
         "size": {
            "x": 205.04265636696874,
            "y": 24.69701463243601
         },
         "label_type": "box",
         "centre": {
            "x": 207.1564470117294,
            "y": 126.23729253273952
         }
      },
      {
         "object_id": 12,
         "label_class": "container",
         "size": {
            "x": 17.80482450245387,
            "y": 21.250919567444924
         },
         "label_type": "box",
         "centre": {
            "x": 97.4557541095136,
            "y": 126.23729253273952
         }
      },
      {
         "object_id": 13,
         "label_class": "container",
         "size": {
            "x": 14.933078614961303,
            "y": 21.825268744943443
         },
         "label_type": "box",
         "centre": {
            "x": 82.23550090580304,
            "y": 125.95011794399025
         }
      },
      {
         "object_id": 14,
         "label_class": "container",
         "size": {
            "x": 14.358729437462799,
            "y": 21.25091956744494
         },
         "label_type": "box",
         "centre": {
            "x": 67.589596879591,
            "y": 125.0885941777425
         }
      },
      {
         "object_id": 15,
         "label_class": "container",
         "size": {
            "x": 15.507427792459815,
            "y": 21.25091956744494
         },
         "label_type": "box",
         "centre": {
            "x": 52.65651826462968,
            "y": 125.0885941777425
         }
      },
      {
         "object_id": 16,
         "label_class": "container",
         "size": {
            "x": 16.65612614745685,
            "y": 21.825268744943443
         },
         "label_type": "box",
         "centre": {
            "x": 36.574741294671355,
            "y": 125.37576876649175
         }
      },
      {
         "object_id": 17,
         "label_class": "container",
         "size": {
            "x": 16.656126147456842,
            "y": 23.548316277438985
         },
         "label_type": "box",
         "centre": {
            "x": 20.49296432471302,
            "y": 123.93989582274548
         }
      },
      {
         "object_id": 18,
         "label_class": "container",
         "size": {
            "x": 12.06133272746875,
            "y": 24.122665454937504
         },
         "label_type": "box",
         "centre": {
            "x": 6.134234887250224,
            "y": 123.65272123399622
         }
      },
      {
         "object_id": 19,
         "label_class": "container",
         "size": {
            "x": 103.38285194973216,
            "y": 28.717458874925583
         },
         "label_type": "box",
         "centre": {
            "x": 142.54216454314678,
            "y": 99.53005577905873
         }
      },
      {
         "object_id": 20,
         "label_class": "container",
         "size": {
            "x": 100.51110606223958,
            "y": 31.014855584919644
         },
         "label_type": "box",
         "centre": {
            "x": 247.3608894366252,
            "y": 102.40180166655128
         }
      },
      {
         "object_id": 21,
         "label_class": "container",
         "size": {
            "x": 67.77320294482439,
            "y": 37.332696537403265
         },
         "label_type": "box",
         "centre": {
            "x": 331.5030439401572,
            "y": 104.98637296529458
         }
      },
      {
         "object_id": 22,
         "label_class": "container",
         "size": {
            "x": 21.250919567444953,
            "y": 15.507427792459836
         },
         "label_type": "box",
         "centre": {
            "x": 335.23631359389753,
            "y": 127.38599088773654
         }
      },
      {
         "object_id": 23,
         "label_class": "container",
         "size": {
            "x": 20.67657038994639,
            "y": 16.65612614745683
         },
         "label_type": "box",
         "centre": {
            "x": 355.6257093950947,
            "y": 128.53468924273358
         }
      },
      {
         "object_id": 24,
         "label_class": "container",
         "size": {
            "x": 21.250919567444953,
            "y": 16.081776969958327
         },
         "label_type": "box",
         "centre": {
            "x": 376.5894543737904,
            "y": 128.2475146539843
         }
      },
      {
         "object_id": 25,
         "label_class": "container",
         "size": {
            "x": 40.20444242489583,
            "y": 18.953522857450892
         },
         "label_type": "box",
         "centre": {
            "x": 406.16843701496373,
            "y": 129.10903842023208
         }
      },
      {
         "object_id": 26,
         "label_class": "container",
         "size": {
            "x": 133.24900917965476,
            "y": 53.988822684860125
         },
         "label_type": "box",
         "centre": {
            "x": 431.43980082489827,
            "y": 93.7865640040736
         }
      }
   ],
   "complete": null,
   "image_filename": "0035.jpg"
}